rsaw/v5/RsawErrors.py
rsaw/v5/aync_rsa.py
rsaw/v5/rsa.py
rsaw-0.8.dist-info/METADATA
rsaw-0.8.dist-info/WHEEL
rsaw-0.8.dist-info/top_level.txt
rsaw-0.8.dist-info/RECORD
